execenv/__init__.py
execenv/config.py
execenv/dotenv.py
execenv/py.typed
execenv/utils.py
execenv/verbose.py
execenv-0.1.1.dist-info/LICENSE
execenv-0.1.1.dist-info/METADATA
execenv-0.1.1.dist-info/WHEEL
execenv-0.1.1.dist-info/entry_points.txt
execenv-0.1.1.dist-info/RECORD
