Metadata-Version: 2.1
Name: execenv
Version: 0.1.1
Summary: Run command with a certain environment.
Home-page: https://github.com/zyf722/execenv
License: MIT
Keywords: cli,commandline,env,environment,environment variables
Author: MaxMixAlex
Author-email: MaxMixAlex@protonmail.com
Requires-Python: >=3.8,<4.0
Classifier: Development Status :: 4 - Beta
Classifier: Environment :: Console
Classifier: Intended Audience :: Developers
Classifier: License :: OSI Approved :: MIT License
Classifier: Operating System :: OS Independent
Classifier: Programming Language :: Python
Classifier: Programming Language :: Python :: 3
Classifier: Programming Language :: Python :: 3.8
Classifier: Programming Language :: Python :: 3.9
Classifier: Programming Language :: Python :: 3.10
Classifier: Programming Language :: Python :: 3.11
Classifier: Programming Language :: Python :: 3.12
Classifier: Topic :: Software Development
Classifier: Topic :: System
Classifier: Topic :: Terminals
Classifier: Typing :: Typed
Provides-Extra: rich
Requires-Dist: auto-click-auto (>=0.1.5,<0.2.0)
Requires-Dist: click (>=8.1.7,<9.0.0)
Requires-Dist: rich-click (>=1.8.3,<2.0.0) ; extra == "rich"
Project-URL: Repository, https://github.com/zyf722/execenv
